connections_sdk/__init__.py
connections_sdk/client.py
connections_sdk/config.py
connections_sdk/exceptions.py
connections_sdk/models.py
connections_sdk/providers/adyen.py
connections_sdk/providers/checkout.py
connections_sdk/utils/__init__.py
connections_sdk/utils/model_utils.py
connections_sdk/utils/request_client.py
connections_sdk-3.2.1.dist-info/LICENSE
connections_sdk-3.2.1.dist-info/METADATA
connections_sdk-3.2.1.dist-info/WHEEL
connections_sdk-3.2.1.dist-info/RECORD
