Metadata-Version: 2.1
Name: connections_sdk
Version: 3.2.1
Summary: A Python SDK for payment processing
Author: Basis Theory
Author-email: support@basistheory.com
Requires-Python: >=3.8
Classifier: Programming Language :: Python :: 3
Classifier: Programming Language :: Python :: 3.8
Classifier: Programming Language :: Python :: 3.9
Classifier: Programming Language :: Python :: 3.10
Classifier: Programming Language :: Python :: 3.11
Classifier: Programming Language :: Python :: 3.12
Classifier: Programming Language :: Python :: 3.13
Requires-Dist: deepmerge (>=2.0,<3.0)
Requires-Dist: faker (>=34.0.0,<35.0.0)
Requires-Dist: requests (>=2.32.2)
